{
  "period": "2026-05-13(수) ~ 2026-05-19(화)",
  "updated_at": "2026-05-19T02:38:17.264199+09:00",
  "furiosa_daily": [
    {
      "title": "노타, 1분기 매출 35.8억…53.6배 성장",
      "url": "http://www.hansbiz.co.kr/news/articleView.html?idxno=839475",
      "date": "05-18",
      "summary": "노타는 1분기 매출이 35.8억 원으로, 전년 대비 53.6배 성장했다고 발표했다. 이 회사는 삼성전자와의 협력을 통해 모바일 분야에서 AI 모델 최적화 기술을 공급하고 있으며, 퓨리오사AI와의 데이터센터 및 모빌린트와의 엣지 AI 협력도 진행 중이다. 이러한 성장은 노타의 AI 최적화 기술이 다양한 산업에 적용되고 있음을 보여주며, 향후 클라우드 인프라로의 확장도 기대된다."
    },
    {
      "title": "[ESG경영 우수사례]시스원, 국산 NPU 기반 '저전력 AX' 시장 정조준…ESG...",
      "url": "https://www.etnews.com/20260518000367",
      "date": "05-18",
      "summary": "시스원은 퓨리오사AI와 공공부문 총판 계약을 체결하여 저전력 AX 시장에 진출할 계획이다. 이 협력을 통해 시스원은 차세대 신경망처리장치(NPU) '레니게이드(RNGD)'를 공급하며, 기존의 기술력을 바탕으로 시장 점유율을 확대할 예정이다. 이는 국내 AI 반도체 시장에서의 경쟁력을 강화하는 중요한 발판이 될 것으로 보인다."
    },
    {
      "title": "엑스페릭스, 1분기 흑자전환…AI 사업 본격화",
      "url": "https://news.dealsitetv.com/articles/170560",
      "date": "05-18",
      "summary": "엑스페릭스는 퓨리오사AI와의 협력을 통해 AI 통합 솔루션 사업을 본격화하고 있다. 이 회사는 퓨리오사AI의 고성능 NPU 'RNGD' 서버에 자사의 AI 소프트웨어를 통합하여 사업 포트폴리오를 확대하고 있다. 이러한 협력은 AI 중심의 사업 확장을 가속화하며, 엑스페릭스의 재무 성과에도 긍정적인 영향을 미치고 있다."
    },
    {
      "title": "엑스페릭스, 순익 흑자 전환⋯관계기업 실적↑",
      "url": "http://www.inews24.com/view/1969403",
      "date": "05-18",
      "summary": "엑스페릭스는 순익 흑자 전환을 이루며, 퓨리오사AI와의 협력을 통해 AI 사업 포트폴리오를 확대하고 있다. 이 회사는 퓨리오사AI의 NPU 'RNGD' 서버에 자사의 AI 소프트웨어와 에이전틱 AI를 통합하여 새로운 솔루션을 제공할 예정이다. 이러한 전략은 엑스페릭스의 경쟁력을 높이고, AI 시장에서의 입지를 강화하는 데 기여할 것으로 예상된다."
    },
    {
      "title": "이억원 금융위원장 \"국민성장펀드, 금융 패러다임 전환\"",
      "url": "https://www.pointdaily.co.kr/news/articleView.html?idxno=305280",
      "date": "05-18",
      "summary": "이억원 금융위원장은 퓨리오사AI를 방문하여 국내 AI 반도체 기업의 현황을 점검하고, 국민성장펀드를 통한 금융 패러다임 전환을 강조했다. 이 자리에서 그는 AI 산업의 중요성과 정부의 지원 필요성을 언급하며, 국내 기업들이 글로벌 시장에서 경쟁력을 갖출 수 있도록 돕겠다고 밝혔다. 이는 AI 산업의 발전을 위한 정책적 의지를 보여주는 중요한 발언이다."
    }
  ],
  "furiosa_weekly": [
    {
      "title": "노타, 솔루션 사업 확대로 1분기 매출 54배 성장…36억원",
      "url": "https://www.etnews.com/20260518000259",
      "date": "05-18",
      "summary": "노타는 1분기 매출이 54배 성장하며 36억 원을 기록했다고 밝혔다. 이 회사는 삼성전자, Arm, 퓨리오사AI, 모빌린트 등과의 협력을 통해 AI 최적화 기술을 다양한 분야에 적용하고 있다. 노타의 이러한 성장은 AI 기술의 확산과 함께 클라우드 인프라로의 확장을 통해 더욱 가속화될 것으로 보인다."
    },
    {
      "title": "노타, AI 최적화 기술로 1분기 매출 53배 '껑충'",
      "url": "https://zdnet.co.kr/view/?no=20260518102749",
      "date": "05-18",
      "summary": "노타는 AI 최적화 기술을 통해 1분기 매출이 53배 증가했다고 발표했다. 퓨리오사AI와의 데이터센터 협력 및 모빌린트와의 엣지 AI 협력을 통해 사업 영역을 확장하고 있으며, 최근 클라우드 인프라로의 진출도 모색하고 있다. 이는 노타가 AI 시장에서의 경쟁력을 강화하고, 다양한 산업에 기여할 수 있는 기반을 마련하고 있음을 보여준다."
    },
    {
      "title": "“AI는 결국 최적화 싸움”…노타, 1분기 매출 35.8억 기록하며 성장세...",
      "url": "https://www.venturesquare.net/1082809/",
      "date": "05-18",
      "summary": "노타는 1분기 매출이 35.8억 원으로, AI 시장의 변화에 발맞춰 성장세를 이어가고 있다. 퓨리오사AI와의 데이터센터 및 모빌린트와의 엣지 AI 협력 외에도 클라우드 인프라로의 사업 확장을 추진하고 있다. 이러한 전략은 AI 모델 최적화의 중요성이 커지는 가운데, 노타의 시장 경쟁력을 더욱 높일 것으로 예상된다."
    },
    {
      "title": "[더벨][산은 넥스트라운드 IN 실리콘밸리] 업스테이지부터 퓨리오사AI까...",
      "url": "https://www.thebell.co.kr/free/content/ArticleView.asp?key=202605141607149440102152",
      "date": "05-18",
      "summary": "퓨리오사AI는 현재 8500억 원 규모의 프리IPO 라운드를 진행 중이며, 하이퍼엑셀과 엑시나 등 다른 기업들도 대규모 신규 투자 유치를 추진하고 있다. 이러한 투자 유치는 퓨리오사AI의 성장 가능성을 높이고, 국내 AI 반도체 시장의 활성화에 기여할 것으로 보인다. 이는 AI 산업의 발전과 경쟁력 강화를 위한 중요한 이정표가 될 것이다."
    },
    {
      "title": "[더벨][코스닥 메자닌 프리즘] 엑스페릭스, ID 중심 사업 개편 시동",
      "url": "https://www.thebell.co.kr/free/content/ArticleView.asp?key=202605131625295280103551",
      "date": "05-18",
      "summary": "ID는 퓨리오사AI에 대한 지속적인 투자를 통해 메타와의 관계에서 반사이익을 보고 있다. 퓨리오사AI가 메타 투자를 거절했음에도 불구하고, 초기 투자 라운드부터의 인연은 ID에게 긍정적인 영향을 미치고 있다. 이는 퓨리오사AI의 성장과 함께 ID의 투자 전략이 성공적으로 작용하고 있음을 나타낸다."
    }
  ],
  "companies": [
    {
      "name": "NVIDIA",
      "region": "global",
      "items": [
        {
          "title": "Prediction : Nvidia Stock Will Hit $300 by the End of 2026",
          "url": "https://finance.yahoo.com/markets/stocks/articles/prediction-nvidias-stock-hit-300-142000642.html",
          "date": "05-18",
          "summary": "NVIDIA의 주가가 2026년 말까지 300달러에 도달할 것이라는 예측이 나왔다. 이는 AI 및 데이터 센터 수요 증가에 따른 것으로, NVIDIA의 기술력이 시장에서 높은 평가를 받고 있다는 것을 반영한다. 이러한 예측은 투자자들에게 긍정적인 신호로 작용할 가능성이 높다.",
          "bd_perspective": "NVIDIA의 주가 상승 예측은 Furiosa의 시장 경쟁력을 위협할 수 있다."
        },
        {
          "title": "Trump Bought Nvidia Stock One Week Before His Own Government Approved a Billion - Dollar Nvidia Chip Deal With China",
          "url": "https://www.ibtimes.co.uk/trump-nvidia-stock-trades-ethics-concerns-1797424",
          "date": "05-18",
          "summary": "도널드 트럼프 전 미국 대통령이 자신의 정부가 중국과의 10억 달러 규모의 NVIDIA 칩 거래를 승인하기 불과 일주일 전에 NVIDIA 주식을 매입한 사실이 드러났다. 이 사건은 정치적 영향력이 기업 거래에 미치는 영향을 보여주며, NVIDIA의 시장 지배력을 더욱 강화할 수 있는 요소로 작용할 수 있다. 이러한 상황은 기업의 윤리적 경영에 대한 논란을 불러일으킬 수 있다.",
          "bd_perspective": "정치적 요인이 NVIDIA의 시장 지배력에 긍정적 영향을 미칠 수 있어 Furiosa에 위협이 될 수 있다."
        },
        {
          "title": "The Real Reason Nvidia Cannot Keep Up With Its Own Demand",
          "url": "https://www.forbes.com/sites/greatspeculations/2026/05/18/the-real-reason-nvidia-cannot-keep-up-with-its-own-demand/",
          "date": "05-18",
          "summary": "NVIDIA가 자사의 수요를 충족시키지 못하는 이유는 공급망 문제와 생산 능력의 한계 때문이다. AI 칩에 대한 수요가 급증하면서 NVIDIA는 생산량을 늘리기 위해 노력하고 있지만, 여전히 공급 부족 현상이 지속되고 있다. 이는 AI 칩 시장에서의 경쟁이 치열해지고 있음을 나타내며, 다른 기업들에게 기회가 될 수 있다.",
          "bd_perspective": "NVIDIA의 공급 문제는 Furiosa에게 시장 점유율 확대의 기회를 제공할 수 있다."
        }
      ]
    },
    {
      "name": "Tenstorrent",
      "region": "global",
      "items": [
        {
          "title": "Smallest . ai and Tenstorrent Partnership Democratises Voice AI - 4x reduction in cost through hardware acceleration",
          "url": "https://www.design-reuse.com/news/202530526-smallest-ai-and-tenstorrent-partnership-democratises-voice-ai-4x-reduction-in-cost-through-hardware-acceleration/",
          "date": "05-18",
          "summary": "Tenstorrent와 Smallest . ai가 파트너십을 체결하여 음성 AI의 비용을 4배 줄이는 하드웨어 가속 솔루션을 제공하기로 했다. 이 협력은 음성 AI 기술의 민주화를 목표로 하며, 더 많은 기업들이 AI 기술을 활용할 수 있도록 지원할 예정이다. 이는 AI 시장의 접근성을 높이는 중요한 발전으로 평가된다.",
          "bd_perspective": "Tenstorrent의 비용 절감 솔루션은 Furiosa의 경쟁력을 강화할 수 있는 기회를 제공한다."
        }
      ]
    },
    {
      "name": "Groq",
      "region": "global",
      "items": [
        {
          "title": "Top 25+ AI Chip Makers: NVIDIA & Its Competitors - AIMultiple",
          "url": "https://news.google.com/rss/articles/CBMiTkFVX3lxTE9UYlQtNjVDT09maWxpR0pGbEU0MGxYaDdad1VzYnp6cXBTcjc4RlY0TXJ0SVVvb0NTU19DdkVCbFFOVjk1MUNmdUg4UjhEdw?oc=5",
          "date": "05-15",
          "summary": "AIMultiple이 발표한 보고서에 따르면, NVIDIA와 그 경쟁자들이 AI 칩 제조업체 상위 25위에 포함되었다. 이 보고서는 AI 칩 시장의 경쟁 구도를 분석하며, 각 기업의 기술력과 시장 점유율을 비교하고 있다. Furiosa와 같은 신생 기업들은 이러한 경쟁 환경에서 차별화된 기술력을 갖추는 것이 중요하다.",
          "bd_perspective": "상위 기업들의 경쟁력 분석은 Furiosa의 전략 수립에 중요한 참고자료가 될 수 있다."
        },
        {
          "title": "How the NVIDIA Vera Rubin Platform is Solving Agentic AI’s Scale-Up Problem | NVIDIA Technical Blog - NVIDIA Developer",
          "url": "https://news.google.com/rss/articles/CBMirgFBVV95cUxQWl9WTHFiREZfWkhfbVBkSFBaT2ZhNE0zYjNWck5rRlNLNjJ6amJ0VDRjRDRwcnpwcTY3TW1vNHh5SXBEcjlhVURRS0YyWW9qRWZiSWxpYUVkeW53NC1ldkpjMWRHeUlVTEZkaV9SZ2xuY2RqbjRrVmc0M19md2N0R2F2eXJISzlsM3o2Qm01NHQtU2ZTOEQxOXBFSWFhMWJpUjB6YnZ2c2s5NkR2OVE?oc=5",
          "date": "05-15",
          "summary": "NVIDIA의 Vera Rubin 플랫폼이 에이전틱 AI의 확장 문제를 해결하는 데 기여하고 있다는 내용이 기술 블로그에 게재되었다. 이 플랫폼은 AI 모델의 대규모 배포를 용이하게 하여, AI 기술의 상용화를 가속화할 수 있는 가능성을 지니고 있다. 이는 NVIDIA가 시장에서의 우위를 더욱 강화할 수 있는 기회를 제공한다.",
          "bd_perspective": "NVIDIA의 기술 발전은 Furiosa의 경쟁력을 더욱 위협할 수 있다."
        }
      ]
    },
    {
      "name": "SambaNova",
      "region": "global",
      "items": [
        {
          "title": "SambaNova Challenges Cerebras Strategy",
          "url": "https://www.marketscreener.com/news/sambanova-challenges-cerebras-strategy-ce7f5bd2d081f22c",
          "date": "05-15",
          "summary": "SambaNova가 Cerebras의 전략에 도전하고 있다는 소식이 전해졌다. SambaNova는 자사의 AI 솔루션을 통해 Cerebras의 시장 점유율을 위협할 수 있는 가능성을 가지고 있으며, 이는 AI 칩 시장의 경쟁을 더욱 치열하게 만들 것으로 예상된다. 이러한 경쟁은 기술 혁신을 촉진할 수 있는 긍정적인 요인으로 작용할 수 있다.",
          "bd_perspective": "SambaNova의 경쟁력 강화는 Furiosa에게 위협이 될 수 있다."
        },
        {
          "title": "Intel Sambanova deal gets U . S . antitrust clearance",
          "url": "https://news.az/news/int-el-s-sambanova-deal-gets-us-antitrust-clearance",
          "date": "05-02",
          "summary": "SambaNova가 Intel과의 거래에 대해 미국 반독점 당국의 승인을 받았다. 이는 SambaNova가 Intel의 자원을 활용하여 AI 칩 시장에서의 입지를 더욱 강화할 수 있는 기회를 제공한다. 이러한 협력은 AI 칩 기술의 발전과 시장 경쟁에 중요한 영향을 미칠 것으로 보인다.",
          "bd_perspective": "Intel과의 협력은 SambaNova의 경쟁력을 높여 Furiosa에 위협이 될 수 있다."
        }
      ]
    },
    {
      "name": "Cerebras",
      "region": "global",
      "items": [
        {
          "title": "Cerebras IPO: Wafer-Scale Performance, Wafer-Scale Pricing (NASDAQ:CBRS) - Seeking Alpha",
          "url": "https://news.google.com/rss/articles/CBMingFBVV95cUxNanpMQlJSek0tMlhyckszcUJWR3hRVllWd2lXUENPb1ZGRXV6TWw2ZS0yblZUcFJoT1RNelUzU2JickdUOU1HVmJobllpallJUzlIRE5oeHlrNWVrX3p1bTVadE9rVW5TOHRnekZjUnl4WHdac3RwRlJOeFdkaUlpcmRxSVJjQnROandWYmZRUVg2U3RBekZSR2N0QVRudw?oc=5",
          "date": "05-19",
          "summary": "Cerebras가 나스닥에 상장하며 웨이퍼 스케일 성능과 가격을 강조하고 있다. 이 IPO는 Cerebras의 기술력이 시장에서 큰 주목을 받고 있음을 나타내며, AI 칩 시장에서의 경쟁을 더욱 치열하게 만들 것으로 예상된다. Cerebras의 성공적인 상장은 다른 기업들에게도 긍정적인 신호로 작용할 수 있다.",
          "bd_perspective": "Cerebras의 IPO 성공은 Furiosa에게 시장의 경쟁 강도를 높일 수 있는 신호다."
        },
        {
          "title": "AI chip giant Cerebras soars after blockbuster Nasdaq debut - Fox Business",
          "url": "https://news.google.com/rss/articles/CBMiW0FVX3lxTE84eWFLVlQ5YVlGbW1KUHlFNE1ZS09tQ29ZZ0I4aGFjTHFmcUdpQkl4REY0VXBuVTRCcWFpc0lOZHVTQ2U3RktJbHFTYkRqeS1NYkRRV09yWWktM28?oc=5",
          "date": "05-18",
          "summary": "AI 칩 대기업 Cerebras가 나스닥에 성공적으로 상장한 후 주가가 급등했다. 이는 Cerebras의 웨이퍼 스케일 기술이 시장에서 큰 관심을 받고 있다는 것을 보여준다. 이러한 성장은 AI 칩 시장의 투자 매력을 높이고, 경쟁사들에게도 긍정적인 영향을 미칠 수 있다.",
          "bd_perspective": "Cerebras의 주가 상승은 Furiosa의 투자 유치에 부정적인 영향을 미칠 수 있다."
        },
        {
          "title": "What you need to know about Nvidia competitor Cerebras after wild IPO - CNBC",
          "url": "https://news.google.com/rss/articles/CBMid0FVX3lxTE1GdkxHV19ncHBPam8teHJNcEdmam9nUV9uWURvZEI5NXFpS0o0ZVVqTW5LaU9XM3dpMGdUd1hFNGFZakhabnpKcmxqQzJreVBna0d4T1hMVjh4OTE2c0U5QTgydUxQUXFOM3NCcnpzcm9DMTZtWkY00gF8QVVfeXFMT2thNjdFWFpiWXMzTVNHZ0todGk0S2l1dEVzLXAtaEJidnNvQVRKa1FuaS0tWTBXUHR0b2Q0RmNUVDZFaThfbXJMUjdsaUg0blhhSG5sRmZuZ2tJUWNTMjRfTTlpbGJVYnpZeEJ0Y3FvWFpMVHlFcFZkZFBzcA?oc=5",
          "date": "05-16",
          "summary": "Cerebras의 IPO에 대한 분석이 진행되며, NVIDIA의 주요 경쟁자로서의 위치가 강조되고 있다. Cerebras는 웨이퍼 스케일 기술을 통해 AI 칩 시장에서의 차별화를 꾀하고 있으며, 이는 Furiosa와 같은 신생 기업들에게 도전 과제가 될 수 있다. 시장의 반응은 Cerebras의 기술력에 대한 신뢰를 나타낸다.",
          "bd_perspective": "Cerebras의 기술적 차별화는 Furiosa의 시장 전략에 도전이 될 수 있다."
        }
      ]
    },
    {
      "name": "Rebellions",
      "region": "korea",
      "items": [
        {
          "title": "국민성장펀드, '금융 패러다임 전환' 시험대 올라…민간 유도 본격화",
          "url": "https://www.sidae.com/article/2026051815322265964",
          "date": "05-18",
          "summary": "리벨리온은 국민성장펀드를 통해 AI 반도체 스타트업에 직접 지분투자를 진행하고 있다. 이들은 기술이 실제 제품으로 이어질 수 있도록 지원하며, 생태계 확장 효과를 중시하는 방향으로 사업을 전개하고 있다. 이는 AI 반도체 시장의 발전에 긍정적인 영향을 미칠 것으로 예상된다.",
          "bd_perspective": "리벨리온의 투자 전략은 Furiosa의 생태계 확장에 기회가 될 수 있다."
        }
      ]
    },
    {
      "name": "DeepX",
      "region": "korea",
      "items": [
        {
          "title": "딥엑스-울트라리틱스, AI 반도체 플랫폼 통합",
          "url": "http://www.hansbiz.co.kr/news/articleView.html?idxno=839241",
          "date": "05-17",
          "summary": "딥엑스가 울트라리틱스와 협력하여 AI 반도체 플랫폼을 통합했다. 개발자들은 이 통합을 통해 복잡한 변환 과정 없이 AI 모델을 딥엑스 칩에 최적화할 수 있게 되었다. 이는 AI 모델 개발의 효율성을 크게 향상시킬 것으로 기대된다.",
          "bd_perspective": "딥엑스의 통합 플랫폼은 Furiosa의 기술 개발에 참고할 수 있는 사례가 될 수 있다."
        },
        {
          "title": "딥엑스, 세계 표준 AI 모델 YOLO 플랫폼에 네이티브 통합",
          "url": "https://zdnet.co.kr/view/?no=20260515100731",
          "date": "05-15",
          "summary": "딥엑스가 울트라리틱스와 협력하여 YOLO 플랫폼에 네이티브 통합을 진행했다. 이를 통해 개발자들은 단 한 줄의 명령어로 AI 모델을 딥엑스 칩에 최적화할 수 있게 되었다. 이러한 기술적 진보는 AI 모델 배포의 효율성을 높이는 데 기여할 것으로 보인다.",
          "bd_perspective": "딥엑스의 기술적 진보는 Furiosa의 개발 전략에 긍정적인 영향을 미칠 수 있다."
        },
        {
          "title": "딥엑스, 세계 1위 객체인식 AI 플랫폼과 '맞손'…글로벌 표준 생태계 정...",
          "url": "https://view.asiae.co.kr/article/2026051514522218003",
          "date": "05-15",
          "summary": "딥엑스가 객체 인식 AI 모델 YOLO 개발사인 울트라리틱스와 전략적 기술 협력을 체결했다. 이번 협력은 딥엑스의 신경망처리장치(NPU)가 글로벌 표준 플랫폼에 네이티브 형태로 통합되는 것을 목표로 한다. 이는 AI 기술의 표준화를 촉진할 수 있는 중요한 발전으로 평가된다.",
          "bd_perspective": "딥엑스의 협력은 Furiosa의 기술 표준화 전략에 참고할 수 있는 사례가 될 수 있다."
        }
      ]
    },
    {
      "name": "HyperAccel",
      "region": "korea",
      "items": [
        {
          "title": "[기획]이진원 하이퍼엑셀 CTO “단기 과제·실패 용인, AI 반도체 성공 ...",
          "url": "https://www.etnews.com/20260515000265",
          "date": "05-17",
          "summary": "하이퍼엑셀의 CTO는 한국이 AI 반도체 시장에서 세계 최고 수준의 역량을 보유하고 있다고 강조했다. 그는 AI 반도체 시장의 급속한 성장 가능성을 언급하며, 한국 기업들이 이 시장을 주도할 기회가 충분하다고 주장했다. 이는 Furiosa에게도 긍정적인 시장 신호로 작용할 수 있다.",
          "bd_perspective": "하이퍼엑셀의 주장에 따라 Furiosa는 한국 시장에서의 기회를 더욱 적극적으로 모색해야 한다."
        },
        {
          "title": "[더벨]하이퍼엑셀, 차세대 AI 반도체 '카르멘' 개발 착수",
          "url": "https://www.thebell.co.kr/free/content/ArticleView.asp?key=202605111357123800101884",
          "date": "05-13",
          "summary": "하이퍼엑셀이 차세대 AI 반도체 '카르멘' 개발에 착수했다. 이들은 AI 발전 속도에 맞춰 2년 주기로 신제품을 출시할 계획이다. 이러한 전략은 AI 반도체 시장에서의 경쟁력을 높이는 데 기여할 것으로 예상된다.",
          "bd_perspective": "하이퍼엑셀의 신제품 개발 계획은 Furiosa에게 시장 경쟁을 더욱 치열하게 만들 수 있다."
        }
      ]
    },
    {
      "name": "Mobilint",
      "region": "korea",
      "items": [
        {
          "title": "노타, 1분기 매출 35.8억…53.6배 성장",
          "url": "http://www.hansbiz.co.kr/news/articleView.html?idxno=839475",
          "date": "05-18",
          "summary": "모바일 AI 최적화 기업 노타가 삼성전자와 협력하여 1분기 매출이 35.8억 원에 달하며 53.6배 성장했다. 노타는 다양한 하드웨어 환경에서 AI 모델 최적화 역량을 검증하고 있으며, 삼성전자와의 협력은 이들의 기술력을 더욱 강화할 것으로 보인다. 이는 AI 반도체 시장의 성장 가능성을 보여준다.",
          "bd_perspective": "노타의 성장은 Furiosa에게도 시장 기회를 제공할 수 있다."
        },
        {
          "title": "노타, 1분기 매출 53배 증가…수주잔고 121억 확보",
          "url": "https://www.newsis.com/view/NISX20260518_0003634184",
          "date": "05-18",
          "summary": "노타는 1분기 매출이 53배 증가하며 수주 잔고 121억 원을 확보했다. 이들은 삼성전자와의 협력으로 AI 최적화 기술을 검증하며, 다양한 분야로 사업을 확장하고 있다. 이는 AI 반도체 시장의 성장 가능성을 더욱 부각시키고 있다.",
          "bd_perspective": "노타의 성장은 Furiosa에게도 경쟁력을 높일 수 있는 기회를 제공한다."
        },
        {
          "title": "노타, 솔루션 사업 확대로 1분기 매출 54배 성장…36억원",
          "url": "https://www.etnews.com/20260518000259",
          "date": "05-18",
          "summary": "노타는 솔루션 사업 확대로 1분기 매출이 54배 성장했다. 이들은 삼성전자, Arm, 퓨리오사AI 등과 협력하여 AI 최적화 기술을 확장하고 있으며, 클라우드 인프라까지 사업을 넓히고 있다. 이는 AI 반도체 시장의 다각화를 보여준다.",
          "bd_perspective": "노타의 사업 확장은 Furiosa에게도 시장 진입 기회를 제공할 수 있다."
        }
      ]
    }
  ]
}